TrackTor/Consensus.db
TrackTor/Error.txt
TrackTor/Start.py
TrackTor/Tabs.py
TrackTor/__init__.py
TrackTor/main.py
TrackTor/Home/Actions.py
TrackTor/Home/DialogBox.py
TrackTor/Home/Edit_Torrc.py
TrackTor/Home/Linux_Torrc_Original
TrackTor/Home/MessageBox.py
TrackTor/Home/Win_Torrc_Original
TrackTor/Home/__init__.py
TrackTor/Icons/1.PNG
TrackTor/Icons/1516821411_torlogo_story.jpg
TrackTor/Icons/2.PNG
TrackTor/Icons/3.PNG
TrackTor/Icons/3TrackTorSplashScreen.png
TrackTor/Icons/4.PNG
TrackTor/Icons/5.PNG
TrackTor/Icons/6.PNG
TrackTor/Icons/7.PNG
TrackTor/Icons/Capture1.PNG
TrackTor/Icons/Icons.py
TrackTor/Icons/Icons.qrc
TrackTor/Icons/Minus.png
TrackTor/Icons/Pause.png
TrackTor/Icons/Play.png
TrackTor/Icons/Plus.png
TrackTor/Icons/Reset.png
TrackTor/Icons/Splashscreen.png
TrackTor/Icons/Tor_Connected.png
TrackTor/Icons/Tor_Disconnected.png
TrackTor/Icons/Torrc.qrc
TrackTor/Icons/TorrcIcon.py
TrackTor/Icons/Welcome-PNG-File.png
TrackTor/Icons/chart-1.jpg
TrackTor/Icons/torrc.sh
TrackTor/Logs_Data/__init__.py
TrackTor/Utilities/Configurations.py
TrackTor/Utilities/Connections.py
TrackTor/Utilities/Graphs.py
TrackTor/Utilities/Interval_Change.py
TrackTor/Utilities/Logs.py
TrackTor/Utilities/Relay_Info.py
TrackTor/Utilities/Resources.py
TrackTor/Utilities/Save_Logs.py
TrackTor/Utilities/StaticInfo.py
TrackTor/Utilities/__init__.py
TrackTor-1.0.dist-info/License.txt
TrackTor-1.0.dist-info/METADATA
TrackTor-1.0.dist-info/WHEEL
TrackTor-1.0.dist-info/entry_points.txt
TrackTor-1.0.dist-info/top_level.txt
TrackTor-1.0.dist-info/RECORD
