Metadata-Version: 2.1
Name: TrackTor
Version: 1.0
Summary: A Monitoring Tool for TOR Network
Home-page: https://github.com/iamhrg/TrackTor
Author: Dr. Pilli Emmanuel Shubhakar, Harsh Gandhi, Ritu Karela, Parul Agrawal
Author-email: espilli.cse@mnit.ac.in, hrgandhi1@gmail.com, ritukarela1234@gmail.com, parulagrawal1507@gmail.com
License: GNU General Public License v3 or later (GPLv3+)
Keywords: TrackTor,Tor,Deep Web,Dark Web,Tor Project,Security,Tracking,Monitoring,Analysing,Nyx,Stem,User Friendly,UI
Platform: UNKNOWN
Classifier: Development Status :: 3 - Alpha
Classifier: Intended Audience :: Developers
Classifier: Intended Audience :: Education
Classifier: Intended Audience :: Science/Research
Classifier: Intended Audience :: Other Audience
Classifier: Topic :: Software Development :: Build Tools
Classifier: Topic :: Software Development :: Libraries :: Python Modules
Classifier: Topic :: Education
Classifier: Topic :: Scientific/Engineering
Classifier: Topic :: Security
Classifier: License :: OSI Approved :: GNU General Public License v3 or later (GPLv3+)
Classifier: Programming Language :: Python :: 3
Classifier: Programming Language :: Python :: 3.4
Classifier: Programming Language :: Python :: 3.5
Classifier: Programming Language :: Python :: 3.6
Classifier: Programming Language :: Python :: 3.7
Requires-Dist: stem
Requires-Dist: argparse
Requires-Dist: numpy
Requires-Dist: pycountry
Requires-Dist: psutil
Requires-Dist: pyqtgraph
Requires-Dist: PyQT5
